dbhelp/__init__.py
dbhelp/__main__.py
dbhelp/helpdb.py
helpdb-0.1.0.dist-info/METADATA
helpdb-0.1.0.dist-info/WHEEL
helpdb-0.1.0.dist-info/top_level.txt
helpdb-0.1.0.dist-info/RECORD
