Metadata-Version: 2.1
Name: helpdb
Version: 0.1.0
Summary: Простая в использовании библиотека для работы с SQLite
Home-page: https://github.com/ваш_username/helpdb
Author: Ваше Имя
Author-email: ваш.email@example.com
License: UNKNOWN
Platform: UNKNOWN
Classifier: Programming Language :: Python :: 3
Classifier: License :: OSI Approved :: MIT License
Classifier: Operating System :: OS Independent
Requires-Python: >=3.6
